eywa.py
eywa_client-0.3.4.dist-info/LICENSE
eywa_client-0.3.4.dist-info/WHEEL
eywa_client-0.3.4.dist-info/METADATA
eywa_client-0.3.4.dist-info/RECORD
