Metadata-Version: 2.1
Name: eywa-client
Version: 0.3.4
Summary: EYWA client library for Python providing JSON-RPC communication, GraphQL queries, and task management for EYWA robots
Keywords: eywa,client,json-rpc,graphql,robotics,automation
Author-email: Robert Gersak <robi@neyho.com>
Requires-Python: >=3.7
Classifier: License :: OSI Approved :: MIT License
Classifier: Programming Language :: Python :: 3
Classifier: Programming Language :: Python :: 3.7
Classifier: Programming Language :: Python :: 3.8
Classifier: Programming Language :: Python :: 3.9
Classifier: Programming Language :: Python :: 3.10
Classifier: Programming Language :: Python :: 3.11
Classifier: Programming Language :: Python :: 3.12
Classifier: Development Status :: 4 - Beta
Classifier: Intended Audience :: Developers
Classifier: Topic :: Software Development :: Libraries :: Python Modules
Requires-Dist: nanoid>=2.0.0
Requires-Dist: aiohttp>=3.8.0
Project-URL: Homepage, https://github.com/neyho/eywa
Project-URL: Issues, https://github.com/neyho/eywa/issues
Project-URL: Repository, https://github.com/neyho/eywa.git
